{
  "article_id": "173",
  "comment_index": 124,
  "image_path": "../data/images/173.png",
  "numbered_ace_sentences": [
    "1. I noticed a pattern in admissions.",
    "2. Legacy applicants were admitted at a significantly higher rate than non-legacy applicants.",
    "3. This difference existed regardless of income.",
    "4. Even at the highest income level, the likelihood of admission was slightly more than 2 times.",
    "5. This likelihood was lower than the likelihood for legacy applicants whose parents had a 99.9 income percentile.",
    "6. I wonder how income affects the school's admission decisions.",
    "7. I ask whether the admission of many legacy students suggests nepotism.",
    "8. I ask what makes a legacy student a better applicant than a non-legacy student.",
    "9. I ask whether the actions of alumni at these schools affect the admission of their children.",
    "10. I come from an urban community.",
    "11. Many of my classmates are not legacy students.",
    "12. Many parents of my classmates are not alumni of these schools.",
    "13. This situation makes admission harder for these classmates.",
    "14. These classmates are already disadvantaged.",
    "15. Legacy status is out of the control of these classmates.",
    "16. Parental or guardian income is out of the control of these classmates.",
    "17. The headline is: Nepotism at Ivy, Advantages Not Even Money Could Buy!"
  ],
  "presence_tags": {
    "1. 1. I noticed a pattern in admissions.": "not_present",
    "2. 2. Legacy applicants were admitted at a significantly higher rate than non-legacy applicants.": "present",
    "3. 3. This difference existed regardless of income.": "present",
    "4. 4. Even at the highest income level, the likelihood of admission was slightly more than 2 times.": "present",
    "5. 5. This likelihood was lower than the likelihood for legacy applicants whose parents had a 99.9 income percentile.": "present",
    "6. 6. I wonder how income affects the school's admission decisions.": "not_present",
    "7. 7. I ask whether the admission of many legacy students suggests nepotism.": "not_present",
    "8. 8. I ask what makes a legacy student a better applicant than a non-legacy student.": "not_present",
    "9. 9. I ask whether the actions of alumni at these schools affect the admission of their children.": "not_present",
    "10. 10. I come from an urban community.": "not_present",
    "11. 11. Many of my classmates are not legacy students.": "not_present",
    "12. 12. Many parents of my classmates are not alumni of these schools.": "not_present",
    "13. 13. This situation makes admission harder for these classmates.": "not_present",
    "14. 14. These classmates are already disadvantaged.": "not_present",
    "15. 15. Legacy status is out of the control of these classmates.": "not_present",
    "16. 16. Parental or guardian income is out of the control of these classmates.": "not_present",
    "17. 17. The headline is: Nepotism at Ivy, Advantages Not Even Money Could Buy!": "not_present"
  }
}