{
  "article_id": "181",
  "comment_index": 56,
  "image_path": "../data/images/181.png",
  "numbered_ace_sentences": [
    "1. Four graphs are shown.",
    "2. The graphs depict energy use and electricity use in China.",
    "3. The graphs depict energy use and electricity use in the United States.",
    "4. The graphs depict energy use and electricity use in India.",
    "5. The graphs depict the worldwide average of energy use and electricity use.",
    "6. Most energy use comes from fossil fuels.",
    "7. Fossil fuels are extremely harmful to the environment.",
    "8. India has a large population.",
    "9. India uses little energy compared to China.",
    "10. India uses little energy compared to the United States.",
    "11. I wonder why India uses little energy compared to China and the United States.",
    "12. India continues to use mainly fossil fuels for energy.",
    "13. China uses more renewable resources as time goes on.",
    "14. The United States uses more renewable resources as time goes on.",
    "15. Among China and the United States and India, the United States seems to be the only country that cuts back on unsustainable resources.",
    "16. Gas is an unsustainable resource.",
    "17. Oil is an unsustainable resource.",
    "18. The United States cuts back on gas.",
    "19. The United States cuts back on oil.",
    "20. The harm of fossil fuels to the environment is widely known.",
    "21. Some other countries continue to use much fossil fuels for their energy system.",
    "22. I wonder why some other countries continue to use much fossil fuels for their energy system."
  ],
  "presence_tags": {
    "1. Four graphs are shown.": {
      "presence": "present",
      "task_type": "value_identification"
    },
    "2. The graphs depict energy use and electricity use in China.": {
      "presence": "not_present",
      "task_type": "not_applicable"
    },
    "3. The graphs depict energy use and electricity use in the United States.": {
      "presence": "not_present",
      "task_type": "not_applicable"
    },
    "4. The graphs depict energy use and electricity use in India.": {
      "presence": "not_present",
      "task_type": "not_applicable"
    },
    "5. The graphs depict the worldwide average of energy use and electricity use.": {
      "presence": "not_present",
      "task_type": "not_applicable"
    },
    "6. Most energy use comes from fossil fuels.": {
      "presence": "present",
      "task_type": "statistical_inference"
    },
    "7. Fossil fuels are extremely harmful to the environment.": {
      "presence": "not_present",
      "task_type": "not_applicable"
    },
    "8. India has a large population.": {
      "presence": "not_present",
      "task_type": "not_applicable"
    },
    "9. India uses little energy compared to China.": {
      "presence": "present",
      "task_type": "arithmetic_computation"
    },
    "10. India uses little energy compared to the United States.": {
      "presence": "present",
      "task_type": "arithmetic_computation"
    },
    "11. I wonder why India uses little energy compared to China and the United States.": {
      "presence": "not_present",
      "task_type": "not_applicable"
    },
    "12. India continues to use mainly fossil fuels for energy.": {
      "presence": "present",
      "task_type": "statistical_inference"
    },
    "13. China uses more renewable resources as time goes on.": {
      "presence": "present",
      "task_type": "statistical_inference"
    },
    "14. The United States uses more renewable resources as time goes on.": {
      "presence": "present",
      "task_type": "statistical_inference"
    },
    "15. Among China and the United States and India, the United States seems to be the only country that cuts back on unsustainable resources.": {
      "presence": "present",
      "task_type": "statistical_inference"
    },
    "16. Gas is an unsustainable resource.": {
      "presence": "not_present",
      "task_type": "not_applicable"
    },
    "17. Oil is an unsustainable resource.": {
      "presence": "not_present",
      "task_type": "not_applicable"
    },
    "18. The United States cuts back on gas.": {
      "presence": "present",
      "task_type": "statistical_inference"
    },
    "19. The United States cuts back on oil.": {
      "presence": "present",
      "task_type": "statistical_inference"
    },
    "20. The harm of fossil fuels to the environment is widely known.": {
      "presence": "not_present",
      "task_type": "not_applicable"
    },
    "21. Some other countries continue to use much fossil fuels for their energy system.": {
      "presence": "not_present",
      "task_type": "not_applicable"
    },
    "22. I wonder why some other countries continue to use much fossil fuels for their energy system.": {
      "presence": "not_present",
      "task_type": "not_applicable"
    }
  }
}