{
  "article_id": "183",
  "comment_index": 53,
  "image_path": "../data/images/183.png",
  "numbered_ace_sentences": [
    "1. I notice the subtitle of the article.",
    "2. The subtitle is \"How involved are parents in their young adult children's lives?\".",
    "3. The subtitle does not match the graphic.",
    "4. The graphic seems to pertain to how involved children are in their parents' lives.",
    "5. The graphic does not seem to pertain to how involved parents are in their young adult children's lives.",
    "6. The graphic would make sense if the graphic measured how much parents reached out to students.",
    "7. I wonder if I should talk to my mother more.",
    "8. I talk to my mother every day.",
    "9. Talking to my mother every day seems normative based on these results.",
    "10. This relates to me.",
    "11. I fit the demographics of this study.",
    "12. I feel represented in the data.",
    "13. I live across the country from my mother.",
    "14. I do not see my mother often.",
    "15. I try to call my mother when I can."
  ],
  "presence_tags": {
    "1. 1. I notice the subtitle of the article.": "not_present",
    "2. 2. The subtitle is \"How involved are parents in their young adult children's lives?\".": "not_present",
    "3. 3. The subtitle does not match the graphic.": "not_present",
    "4. 4. The graphic seems to pertain to how involved children are in their parents' lives.": "not_present",
    "5. 5. The graphic does not seem to pertain to how involved parents are in their young adult children's lives.": "not_present",
    "6. 6. The graphic would make sense if the graphic measured how much parents reached out to students.": "not_present",
    "7. 7. I wonder if I should talk to my mother more.": "not_present",
    "8. 8. I talk to my mother every day.": "not_present",
    "9. 9. Talking to my mother every day seems normative based on these results.": "not_present",
    "10. 10. This relates to me.": "not_present",
    "11. 11. I fit the demographics of this study.": "not_present",
    "12. 12. I feel represented in the data.": "not_present",
    "13. 13. I live across the country from my mother.": "not_present",
    "14. 14. I do not see my mother often.": "not_present",
    "15. 15. I try to call my mother when I can.": "not_present"
  }
}