{
  "$schema": "https://vega.github.io/schema/vega/v6.json",
  "data": [
    {
      "name": "param_1e9efca18e7a2868_store"
    },
    {
      "name": "source_0",
      "values": [
        {
          "comment": "Fewer undocumented immigrants and a stable crime rate. In some areas should be decreasing yet not majorly and these prob\u2026",
          "dim_1": -4.737,
          "dim_2": -0.027,
          "index": 0
        },
        {
          "comment": "I notice that the murder rate has increased\nI wonder why that the murder rate has increased",
          "dim_1": 17.318,
          "dim_2": 6.318,
          "index": 1
        },
        {
          "comment": "I notice that murder count has increased.\nI wonder why they chose to have immigrants be documented and have so much secu\u2026",
          "dim_1": 8.422,
          "dim_2": 15.445,
          "index": 2
        },
        {
          "comment": "I've noticed that the number of murders has increased",
          "dim_1": 16.037,
          "dim_2": 6.218,
          "index": 3
        },
        {
          "comment": "I wonder why immigrants take the illegal way into the United States instead of the legal waywhen it only takes 7-33 mont\u2026",
          "dim_1": -11.243,
          "dim_2": 13.16,
          "index": 4
        },
        {
          "comment": "this graph is showing us how crime is not all caused by immigrants but people assume this because we can't learn to take\u2026",
          "dim_1": -5.773,
          "dim_2": 11.204,
          "index": 5
        },
        {
          "comment": "I noticed that immagrants that are undocumented, there are fewer crimes. I wonder why people that  come from other count\u2026",
          "dim_1": 6.487,
          "dim_2": 16.583,
          "index": 6
        },
        {
          "comment": "One thing that I noticed about the graph is that there is fewer undocumented immigrants and fewer crimes in some cases b\u2026",
          "dim_1": -1.682,
          "dim_2": -11.777,
          "index": 7
        },
        {
          "comment": "WHAT DO I __________ABOUT THIS GRAPH.\n\nNOTICE: Fewer undocumented immigrants - fewer crimes\nWONDER: Why are some people \u2026",
          "dim_1": -7.818,
          "dim_2": -5.77,
          "index": 8
        },
        {
          "comment": "The graphs show that just because the number of illegal immigrants increases, the rate of crime has been decreasing. Thi\u2026",
          "dim_1": -3.601,
          "dim_2": -0.072,
          "index": 9
        },
        {
          "comment": "This graph is showing as more undocumented immegrints have come into the country there has been less violent crimes. I d\u2026",
          "dim_1": -9.233,
          "dim_2": -3.798,
          "index": 10
        },
        {
          "comment": "Despite the popular belief of many Americans eager to point fingers, the majority of undocumented immigrants are not the\u2026",
          "dim_1": 8.999,
          "dim_2": -2.96,
          "index": 11
        },
        {
          "comment": "Many people in the United States hold the belief that immigrants, especially undocumented, increase crime rates. However\u2026",
          "dim_1": 1.881,
          "dim_2": -4.191,
          "index": 12
        },
        {
          "comment": "This graph may appear as a surprise to most Americans. Many Americans believe that undocumented immigrants cause lots of\u2026",
          "dim_1": 2.265,
          "dim_2": -0.864,
          "index": 13
        },
        {
          "comment": "This graph shows that there is a positive impact that most of us were not expecting with the rise in undocumented immigr\u2026",
          "dim_1": 0.39,
          "dim_2": 4.403,
          "index": 14
        },
        {
          "comment": "Most illegal immigrants are not coming to this country to do something violent. Most that are illegal and living in Amer\u2026",
          "dim_1": 0.354,
          "dim_2": 6.593,
          "index": 15
        },
        {
          "comment": "Our country is often called a melting pot, a vast array of people from various cultures and races are embraced and value\u2026",
          "dim_1": -12.66,
          "dim_2": 7.534,
          "index": 16
        },
        {
          "comment": "The first thing that I notice is that correlation equals causation. A lot of these crimes are happening because of immig\u2026",
          "dim_1": 14.791,
          "dim_2": 0.398,
          "index": 17
        },
        {
          "comment": "Looking at this graph after it being confusing to read I can see that this graph is showing the number of violent crime \u2026",
          "dim_1": -6.383,
          "dim_2": -9.393,
          "index": 18
        },
        {
          "comment": "America is a place know for freedom. We (as a nation) are \"free\" and people tend to come to the Americas for that peace/\u2026",
          "dim_1": -9.994,
          "dim_2": 6.952,
          "index": 19
        },
        {
          "comment": "The average student in my high school may look at this graph and think, \"There's no way that's true!\" This is because th\u2026",
          "dim_1": -8.806,
          "dim_2": 8.125,
          "index": 20
        },
        {
          "comment": "This graph shows that immigration into metropolitan areas doesn't definitively show an increase in crime and actually sh\u2026",
          "dim_1": 1.511,
          "dim_2": 10.777,
          "index": 21
        },
        {
          "comment": "This graph disproves a common misconception in regards to illegal immigrants and their effect on crime rates. The media \u2026",
          "dim_1": -8.205,
          "dim_2": 4.299,
          "index": 22
        },
        {
          "comment": "\u201cImmigrants Aren\u2019t Criminals.\u201d Despite whatever generalizations society makes about immigrants, statistically, in commun\u2026",
          "dim_1": -9.604,
          "dim_2": 5.592,
          "index": 23
        },
        {
          "comment": "America, known for its diversity and for lots of illegal immigrants. Being the \u201cMelting Pot\u201d comes with a price however.\u2026",
          "dim_1": -5.63,
          "dim_2": 5.357,
          "index": 24
        },
        {
          "comment": "The word \u201cimmigrants\u201d has a bad stigma around it. Though this should not be the case. The graph in the article shows thi\u2026",
          "dim_1": -12.673,
          "dim_2": 6.134,
          "index": 25
        },
        {
          "comment": "(Part 2)\n\nThe stigma accompanying immigrants is not ok, especially since none of it is based on a serious experience and\u2026",
          "dim_1": -15.905,
          "dim_2": 8.951,
          "index": 26
        },
        {
          "comment": "(Part 1) \n\nThe connection between increased illegal immigrants and increased crime rate is often minimal to none. This d\u2026",
          "dim_1": -13.905,
          "dim_2": 1.953,
          "index": 27
        },
        {
          "comment": "Based on the information from the graph, I notice that there is a fairly loose correlation between the number of undocum\u2026",
          "dim_1": -4.918,
          "dim_2": 1.789,
          "index": 28
        },
        {
          "comment": "In this article, I notice that it would appear that in societies with more undocumented immigrants, crime rates are lowe\u2026",
          "dim_1": -2.955,
          "dim_2": -1.449,
          "index": 29
        },
        {
          "comment": "The article says under the explanation of a trend line that, \u201cthe period 2007 to 2016 tends to decrease as the number of\u2026",
          "dim_1": -3.709,
          "dim_2": 6.934,
          "index": 30
        },
        {
          "comment": "My grandmother and grandfather on my father's side were both immigrants, so I have a strong stance on this subject. Thou\u2026",
          "dim_1": -9.692,
          "dim_2": 3.864,
          "index": 31
        },
        {
          "comment": "Although it's not something that I have spent time thinking about, off the top of my head I would have said that with in\u2026",
          "dim_1": -10.108,
          "dim_2": 8.562,
          "index": 32
        },
        {
          "comment": "Admittedly, I was a bit intimidated by this graph upon first glance. My initial reaction was being overwhelmed by the sh\u2026",
          "dim_1": 4.347,
          "dim_2": -13.867,
          "index": 33
        },
        {
          "comment": "Looking at this graph, it seems that there is a negative correlation between the number of illegal immigrants and the nu\u2026",
          "dim_1": -1.807,
          "dim_2": 5.417,
          "index": 34
        },
        {
          "comment": "The fear mongering used by the GOP that immigrants will only bring crime into our country is proven to be baseless by th\u2026",
          "dim_1": -12.425,
          "dim_2": 10.45,
          "index": 35
        },
        {
          "comment": "Illegal immigrants. That word sparks an insane amount of controversy. You either believe they\u2019re horrible drug lords com\u2026",
          "dim_1": -10.272,
          "dim_2": 11.53,
          "index": 36
        },
        {
          "comment": "My whole life, but especially recently, I have been and become more aware of how extremely tough it is to become a legal\u2026",
          "dim_1": -11.409,
          "dim_2": 7.115,
          "index": 37
        },
        {
          "comment": "As I believe people should come into the U.S legally I understand why they would come illegally, possibly escaping a cor\u2026",
          "dim_1": -9.84,
          "dim_2": -2.345,
          "index": 38
        },
        {
          "comment": "What I notice in this graph and article is that the data is only based on metropolitan areas and only some of the metrop\u2026",
          "dim_1": -1.889,
          "dim_2": 9.564,
          "index": 39
        },
        {
          "comment": "Before I read the stats of the graph, my understanding was with undocumented immigrants comes crime. Now, hear me out. I\u2026",
          "dim_1": -10.913,
          "dim_2": 5.811,
          "index": 40
        },
        {
          "comment": "Before I read this article I always thought that the higher the number of undocumented immigrants the higher crime rate \u2026",
          "dim_1": -6.386,
          "dim_2": -0.978,
          "index": 41
        },
        {
          "comment": "I thought that the correlation between violent crimes and undocumentted immigrants was interesting. People always try to\u2026",
          "dim_1": 0.546,
          "dim_2": 3.029,
          "index": 42
        },
        {
          "comment": "This graph should be shown to everyone in the US. Illegal immigrants are not the source of many of the crimes in the US,\u2026",
          "dim_1": -9.233,
          "dim_2": 2.383,
          "index": 43
        },
        {
          "comment": "The graphs prove that illegal immigrants in the United States do not cause higher crime rates. All of the graphs show a \u2026",
          "dim_1": 0.818,
          "dim_2": -11.797,
          "index": 44
        },
        {
          "comment": "There are many misperceptions about immigrants.  One of them highlighted here is that crime is connected to immigrants. \u2026",
          "dim_1": -11.773,
          "dim_2": 9.59,
          "index": 45
        },
        {
          "comment": "I believe the graph is saying that instead of there being a positive correlation between the number of illegal aliens an\u2026",
          "dim_1": -4.249,
          "dim_2": -8.232,
          "index": 46
        },
        {
          "comment": "This graph really changed my perspective on this topic. Before I looked at the stats, I always had the popular conservat\u2026",
          "dim_1": -8.005,
          "dim_2": 3.214,
          "index": 47
        },
        {
          "comment": "I\u2019m going to be honest, I\u2019m not very good with graphs as my next sentence will prove. The first time I looked at the gra\u2026",
          "dim_1": -4.338,
          "dim_2": 9.226,
          "index": 48
        },
        {
          "comment": "(Part 1)\nThe correlation between undocumented immigrants and crime rate is very weak, but ever so slightly negative for \u2026",
          "dim_1": -12.845,
          "dim_2": 1.672,
          "index": 49
        },
        {
          "comment": "Many people in the United States of America think of undocumented immagrants as criminals. They don\u2019t take the time to l\u2026",
          "dim_1": -11.45,
          "dim_2": 4.263,
          "index": 50
        },
        {
          "comment": "The large graph at the top of the paper only proves that violent crimes have little to do with just illegal immigrants a\u2026",
          "dim_1": 0.464,
          "dim_2": -7.591,
          "index": 51
        },
        {
          "comment": "I\u2019m honestly probably the worse graph reader there is. And this graph had to be hard. But it looks like the more undocum\u2026",
          "dim_1": -4.441,
          "dim_2": 4.424,
          "index": 52
        },
        {
          "comment": "The graph shows the number of violent crime rates in relation to the number of undocumented immigrants. In all areas of \u2026",
          "dim_1": 3.308,
          "dim_2": -1.674,
          "index": 53
        },
        {
          "comment": "(Part 2)\nI wonder if the trend would be different state to stat and what the data is like for other crimes not listed su\u2026",
          "dim_1": -16.008,
          "dim_2": 8.652,
          "index": 54
        },
        {
          "comment": "The graph shows that as the number of undocumented immigrants increases, the number of violent crimes decreases. This is\u2026",
          "dim_1": -2.662,
          "dim_2": 1.779,
          "index": 55
        },
        {
          "comment": "This graph shows a small downward trend in crime as the number of undocumented immigrants increases.  This could mean th\u2026",
          "dim_1": 3.17,
          "dim_2": -13.318,
          "index": 56
        },
        {
          "comment": "I must admit that the way this graph was displayed and described was difficult to understand. However, after a few minut\u2026",
          "dim_1": -11.484,
          "dim_2": -5.551,
          "index": 57
        },
        {
          "comment": "Although I found this graph confusing at first since it is hard to read once I read the article I realized what it was t\u2026",
          "dim_1": -7.772,
          "dim_2": 9.217,
          "index": 58
        },
        {
          "comment": "I notice that the number of violent crimes actually decreases as the number of undocumented immigrants increases. Most p\u2026",
          "dim_1": 1.568,
          "dim_2": -1.545,
          "index": 59
        },
        {
          "comment": "The graphs shown are depicting that the rise of illegal immigrants in the U.S. has increased crime rates. As the number \u2026",
          "dim_1": -0.495,
          "dim_2": -4.403,
          "index": 60
        },
        {
          "comment": "Yet this graph is confusing, it seem that the less undocumented immigrants there are the more violent crimes there are. \u2026",
          "dim_1": 0.99,
          "dim_2": 0.069,
          "index": 61
        },
        {
          "comment": "These graphs show an overall decrease in the crimes committed by undocumented immigrants. I find these results to be exp\u2026",
          "dim_1": -1.488,
          "dim_2": -5.371,
          "index": 62
        },
        {
          "comment": "From what I can see I can see this is only benefitting the areas around them based on the graphs and their gradual downw\u2026",
          "dim_1": 16.246,
          "dim_2": 2.639,
          "index": 63
        },
        {
          "comment": "The points on this graph show the relationship between undocumented immigrants and crime rate. As the amount of immigran\u2026",
          "dim_1": -3.184,
          "dim_2": -9.123,
          "index": 64
        },
        {
          "comment": "Looking at the charts I see a downward trend of all crimes listed except murder when more undocumented immigrants go int\u2026",
          "dim_1": 0.36,
          "dim_2": -2.61,
          "index": 65
        },
        {
          "comment": "This graph is showing a decrease in crimes as the undocumented immigrants enter. I find this very interesting because I \u2026",
          "dim_1": -8.062,
          "dim_2": -11.985,
          "index": 66
        },
        {
          "comment": "The graph is showing a slight decrease in the amount of crimes as the amount of undocumented immigrants goes up. I think\u2026",
          "dim_1": -2.041,
          "dim_2": -6.863,
          "index": 67
        },
        {
          "comment": "In the graph it shows that as immigrants come to America, the crime rates actually start to decrease. It shows that it i\u2026",
          "dim_1": -5.426,
          "dim_2": 9.95,
          "index": 68
        },
        {
          "comment": "The graph is showing the relationship between the number of undocumented immigrants and the crime rates in major cities.\u2026",
          "dim_1": -6.182,
          "dim_2": -10.344,
          "index": 69
        },
        {
          "comment": "This graph for the most part shows that as more illegal immigrants come crime rates decrease. But does less crime Americ\u2026",
          "dim_1": -5.16,
          "dim_2": -4.969,
          "index": 70
        },
        {
          "comment": "The graph shows that as the undocumented immigrants rise the crime rate is lowering. This graph shows that the typical s\u2026",
          "dim_1": -7.105,
          "dim_2": -7.029,
          "index": 71
        },
        {
          "comment": "This graph is showing that for the most part, the amount of undocumented immigrants is rising but the crime rate is fall\u2026",
          "dim_1": -4.313,
          "dim_2": -6.325,
          "index": 72
        },
        {
          "comment": "This graph shows the correlation between crime rates in cities and the number of undocumented immigrants. The article sa\u2026",
          "dim_1": -7.289,
          "dim_2": 6.189,
          "index": 73
        },
        {
          "comment": "Lots of people think that the more undocumented immigrants there are the more crimes there will be, but that is not what\u2026",
          "dim_1": -2.097,
          "dim_2": 0.044,
          "index": 74
        },
        {
          "comment": "This graph shows that although the number of undocumented immigrants is rising, the crime rates are falling. I don\u2019t bel\u2026",
          "dim_1": -5.762,
          "dim_2": -8.26,
          "index": 75
        },
        {
          "comment": "This graph is proving that although there is a belief that the increase of illegal immigrants would cause an increase in\u2026",
          "dim_1": -5.41,
          "dim_2": -9.947,
          "index": 76
        },
        {
          "comment": "The graph is showing that in general, the crime rate is not particularly affected by the amount of undocumented immigran\u2026",
          "dim_1": -4.955,
          "dim_2": -7.341,
          "index": 77
        },
        {
          "comment": "This graph is showing that as the number of undocumented immigrants is rising, the amount of crimes is falling.  I belie\u2026",
          "dim_1": -3.715,
          "dim_2": -5.877,
          "index": 78
        },
        {
          "comment": "The highest point on this graph is where there is a decrease in immigrants and the count of violent crimes, is over 200.\u2026",
          "dim_1": -7.484,
          "dim_2": 6.913,
          "index": 79
        },
        {
          "comment": "There is no correlation between undocumented immigrants and crimes in the United States. Period. All of the graphs\u2019 line\u2026",
          "dim_1": -0.829,
          "dim_2": -9.31,
          "index": 80
        },
        {
          "comment": "This graph is showing that as the number of undocumented immigrants is going up, the number of violent crimes is going d\u2026",
          "dim_1": -7.537,
          "dim_2": -7.727,
          "index": 81
        },
        {
          "comment": "The graph shows the correlation between the number of undocumented immigrants and the violent crime rate in big cities. \u2026",
          "dim_1": -6.429,
          "dim_2": 2.068,
          "index": 82
        },
        {
          "comment": "This graph serves as a refutation for claims that undocumented immigration is dangerous for American citizens. The graph\u2026",
          "dim_1": -10.118,
          "dim_2": -7.983,
          "index": 83
        },
        {
          "comment": "These graphs before me all have one thing in common. They all appear to have a body of points right before the number ze\u2026",
          "dim_1": -1.043,
          "dim_2": -8.338,
          "index": 84
        },
        {
          "comment": "It\u2019s kind of disappointing to have learn that people need visible, physical graphs to show them that undocumented immigr\u2026",
          "dim_1": -4.0,
          "dim_2": 3.719,
          "index": 85
        },
        {
          "comment": "Part 2-\nI believe that the people in our country need to stop stereotyping and start looking at actual data. The United \u2026",
          "dim_1": -15.485,
          "dim_2": 6.551,
          "index": 86
        },
        {
          "comment": "Part 1-\nPrior to viewing these graphs, I would not have expected to see the amount of crime decrease with an increase in\u2026",
          "dim_1": -3.644,
          "dim_2": 1.498,
          "index": 87
        },
        {
          "comment": "When I first looked at this graph I really didn't think it was going to be about undoumented immigrants and crime rates.\u2026",
          "dim_1": -0.756,
          "dim_2": -2.142,
          "index": 88
        },
        {
          "comment": "The graph is showing the correlation between the number of undocumented immigrants and the violent crime rate in big cit\u2026",
          "dim_1": -7.661,
          "dim_2": -9.595,
          "index": 89
        },
        {
          "comment": "The graph is showing how the number of undocumented immigrants has risen and the number of violent crimes have decreased\u2026",
          "dim_1": -9.035,
          "dim_2": -8.326,
          "index": 90
        },
        {
          "comment": "The first thing that I notice is that correlation equals causation. A lot of these crimes are happening because of immig\u2026",
          "dim_1": 14.791,
          "dim_2": 0.398,
          "index": 91
        },
        {
          "comment": "In the large graph, I noticed that the general trend is that violent crime is going down over the years as the number of\u2026",
          "dim_1": 2.857,
          "dim_2": -7.676,
          "index": 92
        },
        {
          "comment": "I notice in all graphs that there\u2019s a cluster right before the graph hits zero and there seems to be no correlation what\u2026",
          "dim_1": 1.482,
          "dim_2": -9.125,
          "index": 93
        },
        {
          "comment": "I notice that in the larger graph, violent crime is on a general decrease as undocumented immigrants increase. This isn\u2019\u2026",
          "dim_1": 2.069,
          "dim_2": -2.732,
          "index": 94
        },
        {
          "comment": "Part one-  Anytime this subject comes up it makes me angst more and more. It is ridiculous that we are even debating the\u2026",
          "dim_1": -15.246,
          "dim_2": 10.082,
          "index": 95
        },
        {
          "comment": "In all six graphs there seems to be a common trend. The amount of crime for more undocumented immigrants is less than th\u2026",
          "dim_1": 0.098,
          "dim_2": 0.589,
          "index": 96
        },
        {
          "comment": "I notice that the graph is relatively the same throughout. It\u2019s roughly a horizontal line that will probably continue to\u2026",
          "dim_1": -2.638,
          "dim_2": -11.045,
          "index": 97
        },
        {
          "comment": "Noticing: I noticed the most crime is between positive 0 and negative 200; I noticed there are more negative crime; I no\u2026",
          "dim_1": 6.027,
          "dim_2": -13.529,
          "index": 98
        },
        {
          "comment": "I noticed that the undocumented immigrants is going up and so is the crime rate.",
          "dim_1": 7.48,
          "dim_2": 13.254,
          "index": 99
        },
        {
          "comment": "I noticed that there are more documented immigrants then undocumented immigrants.  Also that the murder rate is going up\u2026",
          "dim_1": 8.673,
          "dim_2": 14.561,
          "index": 100
        },
        {
          "comment": "In this scatter plot it shows the changes in violent crimes factoring in the number of undocumented immigrants in metro \u2026",
          "dim_1": 8.636,
          "dim_2": -8.117,
          "index": 101
        },
        {
          "comment": "what i noticed the murder graph is positive \nwonder why are all the graphs negative\na title will be the crimes vs undocu\u2026",
          "dim_1": 2.441,
          "dim_2": -14.971,
          "index": 102
        },
        {
          "comment": "As the undocumented immagrants cases go up, then the number of crimes go up. Assaults , robberies, bulgaries, and larson\u2026",
          "dim_1": 7.465,
          "dim_2": 5.608,
          "index": 103
        },
        {
          "comment": "the murder rate goes up",
          "dim_1": 17.594,
          "dim_2": 7.038,
          "index": 104
        },
        {
          "comment": "I notice that there is hardly a relationship between violent crimes and illegal immigration. I wonder why murder was the\u2026",
          "dim_1": 10.953,
          "dim_2": 5.874,
          "index": 105
        },
        {
          "comment": "I noticed that as the number of illegal immigrants decrease so does the crime rate and i wonder if it will continue to d\u2026",
          "dim_1": 4.732,
          "dim_2": 12.164,
          "index": 106
        },
        {
          "comment": "Why are there 180 metropolitan areas ?",
          "dim_1": 11.758,
          "dim_2": 15.579,
          "index": 107
        },
        {
          "comment": "That the only thing increasing is murders while all the others are decreasing. Why is that only the murders are increasi\u2026",
          "dim_1": 16.803,
          "dim_2": 5.396,
          "index": 108
        },
        {
          "comment": "I wonder what states specifically are affected by the most crime.",
          "dim_1": 10.052,
          "dim_2": 1.014,
          "index": 109
        },
        {
          "comment": "Crime and Violence\n\nThe higher the undocumented immigrants the more it will make the line of best fit tilt either up or \u2026",
          "dim_1": 7.533,
          "dim_2": -11.316,
          "index": 110
        },
        {
          "comment": "The more undocumented immigrants we have the more the violent crime rate is going down.",
          "dim_1": 8.348,
          "dim_2": 9.816,
          "index": 111
        },
        {
          "comment": "where are the 180 metropolitan areas that data was collected and  ive noticed that murder rate goes up with more undocum\u2026",
          "dim_1": 10.485,
          "dim_2": 14.991,
          "index": 112
        },
        {
          "comment": "I notice that the number of undocumented immigrants decreases when the number of violent crimes increases. The scatter p\u2026",
          "dim_1": 10.074,
          "dim_2": -6.142,
          "index": 113
        },
        {
          "comment": "Thanks to all students who responded.  Many of you saw something surprising.  That's what makes a great graph.  \n \nYou c\u2026",
          "dim_1": -10.005,
          "dim_2": -14.661,
          "index": 114
        },
        {
          "comment": "this graph is great because it proves that undocumented immigrants don't cause the amount of violent crimes to go up i s\u2026",
          "dim_1": -9.498,
          "dim_2": -9.275,
          "index": 115
        },
        {
          "comment": "notice that as crime rate increases there is a decrease in immigration to the United States. I wonder why people still b\u2026",
          "dim_1": 3.548,
          "dim_2": 14.43,
          "index": 116
        },
        {
          "comment": "I notice that that most of the crimes are under and theres few above.\ni wonder why theres not very many below -400.\ntitl\u2026",
          "dim_1": 8.674,
          "dim_2": 1.975,
          "index": 117
        },
        {
          "comment": "noticing - it decreases in immigration in the United States. \nwondering -   which trend line is for each information. \nt\u2026",
          "dim_1": 5.964,
          "dim_2": -3.812,
          "index": 118
        },
        {
          "comment": "This scatterplot displays the correlation of violent crimes with change in undocumented immigrants. As the number of imm\u2026",
          "dim_1": 9.253,
          "dim_2": -7.844,
          "index": 119
        },
        {
          "comment": "Hi, Parker \u2026\n\nLook at the five small graphs as well as the title of each axis.  The data indicate a negative association\u2026",
          "dim_1": 2.506,
          "dim_2": -13.505,
          "index": 120
        },
        {
          "comment": "This graph actually seems very confusing, I'm not quite sure what is really going on here for the average immigrant.",
          "dim_1": -3.652,
          "dim_2": -12.262,
          "index": 121
        },
        {
          "comment": "This graph marks the changes in violent crimes based on how many undocumented immigrants there are in a specific area. A\u2026",
          "dim_1": 3.871,
          "dim_2": -0.503,
          "index": 122
        },
        {
          "comment": "Hi, Raquel \u2026\nI'm glad you've looking at the rates.  Very good question.\nAnd thanks for the headline!",
          "dim_1": 18.153,
          "dim_2": 8.391,
          "index": 123
        },
        {
          "comment": "I notice that as crime rate increases there is a decrease in immigration to the United States. I wonder why people still\u2026",
          "dim_1": 3.385,
          "dim_2": 14.51,
          "index": 124
        },
        {
          "comment": "Hi, Devyn D from my home state of NJ \u2026.\n\nBe sure you are reading the TITLE of the graph and interpreting the axis correc\u2026",
          "dim_1": -2.576,
          "dim_2": -14.647,
          "index": 125
        },
        {
          "comment": "I found it interesting that as there were fewer undocumented immigrants, there were more violent crimes. According to th\u2026",
          "dim_1": 9.249,
          "dim_2": 3.657,
          "index": 126
        },
        {
          "comment": "Calling for short and catchy headlines that capture the main idea of these graphs.  \n\nWhat headline will tell the story \u2026",
          "dim_1": -9.089,
          "dim_2": -13.297,
          "index": 127
        },
        {
          "comment": "What I noticed - \n\nI noticed while looking at the first graph it seemed as if with the increase of undocumented immigran\u2026",
          "dim_1": 6.197,
          "dim_2": -10.939,
          "index": 128
        },
        {
          "comment": "Title: Crime rate rising with undocumented immigrants.\n\nI wonder why in some areas of the bottom graph why the areas wit\u2026",
          "dim_1": 7.478,
          "dim_2": -9.849,
          "index": 129
        },
        {
          "comment": "I wonder what immigrants have to do with the crimes that are being committed, According to this graph I notice that the \u2026",
          "dim_1": -3.602,
          "dim_2": 12.337,
          "index": 130
        },
        {
          "comment": "I had a lot of trouble understanding this graph, it wasn't very clear to me what it was trying to show, but from what I \u2026",
          "dim_1": -4.755,
          "dim_2": -12.643,
          "index": 131
        },
        {
          "comment": "one of the things I noticed that the begging the crime rates were slow but then it started to get a lot thicker in the m\u2026",
          "dim_1": 11.293,
          "dim_2": 3.629,
          "index": 132
        },
        {
          "comment": "I noticed on the graph that there has recently been a trend of less violent to almost no crimes. There are many more und\u2026",
          "dim_1": 3.646,
          "dim_2": -6.266,
          "index": 133
        },
        {
          "comment": "I think that this graph is saying that when there are more undocumented immigrants, the trend of violent crimes goes dow\u2026",
          "dim_1": 3.915,
          "dim_2": -7.225,
          "index": 134
        },
        {
          "comment": "I was a bit confused on what the graph was trying to show, as it shows no dates for when the data was taken, or if there\u2026",
          "dim_1": -4.8,
          "dim_2": -14.264,
          "index": 135
        },
        {
          "comment": "I notice that the graph has more documented immigrants rather than undocumented. Or at least that is my interpretation b\u2026",
          "dim_1": -11.578,
          "dim_2": -8.455,
          "index": 136
        },
        {
          "comment": "We noticed that there is minimal correlation between the amount of violent crimes and the number of undocumented immigra\u2026",
          "dim_1": 3.952,
          "dim_2": 5.83,
          "index": 137
        },
        {
          "comment": "When we looked at the graphs we noticed that the number of assaults, and robberies have gone down with the number of und\u2026",
          "dim_1": -4.46,
          "dim_2": -2.477,
          "index": 138
        },
        {
          "comment": "We noticed that with more undocumented immigrants, the crime level dropped slightly. We wonder where the data comes from\u2026",
          "dim_1": 5.95,
          "dim_2": -1.952,
          "index": 139
        },
        {
          "comment": "1. We noticed this graph is about the change in undocumented immigrants and violent crimes.  \n\n2. Immigrant info\n\n3. We \u2026",
          "dim_1": 8.091,
          "dim_2": -3.611,
          "index": 140
        },
        {
          "comment": "We noticed that the graph has a corellation between undocumented immigrants and violent crime rates. One thing that we w\u2026",
          "dim_1": 6.027,
          "dim_2": -6.872,
          "index": 141
        },
        {
          "comment": "In this graph,  I notice that there is little correlation between undocumented immigrants and violent crimes. In  additi\u2026",
          "dim_1": 2.55,
          "dim_2": 0.915,
          "index": 142
        },
        {
          "comment": "I notice that this graph shows the statistics of amounts of immigrants (x-axis) and the rates of violent crime (y-axis) \u2026",
          "dim_1": 3.201,
          "dim_2": -9.061,
          "index": 143
        },
        {
          "comment": "Headline: Undocumented immigrants and the crimes\n\nI notice that there is a lack of correlation between the increase in u\u2026",
          "dim_1": 2.298,
          "dim_2": 2.265,
          "index": 144
        },
        {
          "comment": "This graph shows the change in undocumented immigrants and violent crimes in 180 metropolitan areas from 2007-2016. I no\u2026",
          "dim_1": 1.864,
          "dim_2": -0.109,
          "index": 145
        },
        {
          "comment": "I noticed in the first graph that over this 9 year period violent crimes have decreased in relation to undocumented immi\u2026",
          "dim_1": 7.228,
          "dim_2": -6.134,
          "index": 146
        },
        {
          "comment": "Welcome to Wednesday's moderation of  \u201cWhat\u2019s Going On in This Graph?\u201d  \n\nToday\u2019s graphs show the relationship between t\u2026",
          "dim_1": -10.212,
          "dim_2": -14.967,
          "index": 147
        },
        {
          "comment": "This first scatter plot shows the correlation between violent crimes increasing and the change in undocumented immigrant\u2026",
          "dim_1": 9.107,
          "dim_2": -7.012,
          "index": 148
        },
        {
          "comment": "I noticed that there is less violent crimes with less undocumented immigrants",
          "dim_1": 9.022,
          "dim_2": 10.763,
          "index": 149
        },
        {
          "comment": "The Correlation between undocumented Immigrants and crime in major metropolitan.",
          "dim_1": 3.928,
          "dim_2": 4.024,
          "index": 150
        },
        {
          "comment": "I noticed that there is really little correlation between the increase in undocumented immigrants and the increase of vi\u2026",
          "dim_1": -0.748,
          "dim_2": 2.559,
          "index": 151
        },
        {
          "comment": "At first I noticed that the first graph shown at the top relays that the more undocumented immigrants that are present,t\u2026",
          "dim_1": -0.713,
          "dim_2": -0.974,
          "index": 152
        },
        {
          "comment": "I noticed that the more undocumented immigrants that came to the United States decreased the number of violent crimes co\u2026",
          "dim_1": 11.199,
          "dim_2": 10.893,
          "index": 153
        },
        {
          "comment": "By looking at the graph I can tell that the rate of crimes were low when the number of undocumented immigrants increased\u2026",
          "dim_1": -1.817,
          "dim_2": -2.83,
          "index": 154
        },
        {
          "comment": "The graph of overall violent crimes in the U.S. shows that there is no correlation between the amount of immigrants and \u2026",
          "dim_1": 4.132,
          "dim_2": -3.676,
          "index": 155
        },
        {
          "comment": "I noticed that as more undocumented immigrants enter the United States violent crimes such as assaults, robberies, burgl\u2026",
          "dim_1": 10.243,
          "dim_2": 6.96,
          "index": 156
        },
        {
          "comment": "It may be true that the increase of undocumented immigrants in the United States has led to a rise in violent crimes, bu\u2026",
          "dim_1": 11.252,
          "dim_2": 8.715,
          "index": 157
        },
        {
          "comment": "-I noticed that out of all the graphs, the one  with the most increase in undocumented immigrants was murder as that one\u2026",
          "dim_1": 4.226,
          "dim_2": 1.559,
          "index": 158
        },
        {
          "comment": "I noticed that as more undocumented immigrants are present, then the less violent crimes there are; therefore, they have\u2026",
          "dim_1": 7.19,
          "dim_2": 10.401,
          "index": 159
        },
        {
          "comment": "The less undocumented immigrants then there would be less crime.",
          "dim_1": 9.068,
          "dim_2": 12.057,
          "index": 160
        },
        {
          "comment": "@Division 6 Of course we notice that there are fewer violent crimes as the number of undocumented immigrants increase, h\u2026",
          "dim_1": 5.358,
          "dim_2": -3.046,
          "index": 161
        },
        {
          "comment": "Based on the graph, I see that the number of undocumented students increases and the number of violent crimes is not a d\u2026",
          "dim_1": 6.456,
          "dim_2": -0.225,
          "index": 162
        },
        {
          "comment": "It seems that, although the main reason as to why is unknown, the crime rates have overall decreased as the number of un\u2026",
          "dim_1": 6.186,
          "dim_2": 12.503,
          "index": 163
        },
        {
          "comment": "I noticed that on the first graph there is a trend that declines. As they show more detail of the different crimes being\u2026",
          "dim_1": 17.901,
          "dim_2": 4.712,
          "index": 164
        },
        {
          "comment": "Based on the graph, there seems to be a trend of crime decreasing as the number of undocumented immigrants increase. Thi\u2026",
          "dim_1": -2.482,
          "dim_2": -3.613,
          "index": 165
        },
        {
          "comment": "I noticed that the larger amount of undocumented immigrants the lower the violent crimes. However, the murder rate incre\u2026",
          "dim_1": 9.499,
          "dim_2": 7.01,
          "index": 166
        },
        {
          "comment": "According to the data it seems that crime decreases as the amount of immigrants increases. This is most likely due to th\u2026",
          "dim_1": 3.544,
          "dim_2": 11.396,
          "index": 167
        },
        {
          "comment": "I have spoken to my peers, we have all seen the graph and come to a conclusion that the more undocumented there are, the\u2026",
          "dim_1": 6.817,
          "dim_2": 1.17,
          "index": 168
        },
        {
          "comment": "I noticed how murders seem to still be rising as compared to the other forms of illegal crimes.",
          "dim_1": 15.058,
          "dim_2": 6.234,
          "index": 169
        },
        {
          "comment": "I noticed that as more undocumented immigrants are present, then the less violent crimes there are; therefore, they have\u2026",
          "dim_1": 7.74,
          "dim_2": 10.793,
          "index": 170
        },
        {
          "comment": "It seems like the larger the amount of undocumented immigrants the lower the violent crime overall (with an exception to\u2026",
          "dim_1": 8.87,
          "dim_2": 7.772,
          "index": 171
        },
        {
          "comment": "This can be true but the problem can  be that the immigrants cause the crimes or is it the way we think about them or ho\u2026",
          "dim_1": -2.183,
          "dim_2": 13.169,
          "index": 172
        },
        {
          "comment": "My peers and I have perceived that as the number of undocumented immigrants increases, the number of violent crimes has \u2026",
          "dim_1": 10.312,
          "dim_2": 9.391,
          "index": 173
        },
        {
          "comment": "Crime actually seems to reduce and the violent crimes become less violent compared to when there was less immigrants, mo\u2026",
          "dim_1": 5.011,
          "dim_2": 10.485,
          "index": 174
        },
        {
          "comment": "We noticed that there are fewer violent crimes as the number of undocumented immigrants increases.",
          "dim_1": 9.561,
          "dim_2": 10.192,
          "index": 175
        }
      ]
    },
    {
      "name": "source_0_x_domain_dim_1",
      "values": [
        {
          "min": -16.008,
          "max": 18.153
        }
      ]
    },
    {
      "name": "source_0_y_domain_dim_2",
      "values": [
        {
          "min": -14.971,
          "max": 16.583
        }
      ]
    }
  ],
  "signals": [
    {
      "name": "unit",
      "value": {},
      "on": [
        {
          "events": "pointermove",
          "update": "isTuple(group()) ? group() : unit"
        }
      ]
    },
    {
      "name": "param_1e9efca18e7a2868",
      "update": "vlSelectionResolve(\"param_1e9efca18e7a2868_store\", \"union\")"
    },
    {
      "name": "param_1e9efca18e7a2868_dim_1",
      "on": [
        {
          "events": [
            {
              "source": "view",
              "type": "dblclick"
            }
          ],
          "update": "null"
        },
        {
          "events": {
            "signal": "param_1e9efca18e7a2868_translate_delta"
          },
          "update": "panLinear(param_1e9efca18e7a2868_translate_anchor.extent_x, -param_1e9efca18e7a2868_translate_delta.x / width)"
        },
        {
          "events": {
            "signal": "param_1e9efca18e7a2868_zoom_delta"
          },
          "update": "zoomLinear(domain(\"x\"), param_1e9efca18e7a2868_zoom_anchor.x, param_1e9efca18e7a2868_zoom_delta)"
        }
      ]
    },
    {
      "name": "param_1e9efca18e7a2868_dim_2",
      "on": [
        {
          "events": [
            {
              "source": "view",
              "type": "dblclick"
            }
          ],
          "update": "null"
        },
        {
          "events": {
            "signal": "param_1e9efca18e7a2868_translate_delta"
          },
          "update": "panLinear(param_1e9efca18e7a2868_translate_anchor.extent_y, param_1e9efca18e7a2868_translate_delta.y / height)"
        },
        {
          "events": {
            "signal": "param_1e9efca18e7a2868_zoom_delta"
          },
          "update": "zoomLinear(domain(\"y\"), param_1e9efca18e7a2868_zoom_anchor.y, param_1e9efca18e7a2868_zoom_delta)"
        }
      ]
    },
    {
      "name": "param_1e9efca18e7a2868_tuple",
      "on": [
        {
          "events": [
            {
              "signal": "param_1e9efca18e7a2868_dim_1 || param_1e9efca18e7a2868_dim_2"
            }
          ],
          "update": "param_1e9efca18e7a2868_dim_1 && param_1e9efca18e7a2868_dim_2 ? {unit: \"\", fields: param_1e9efca18e7a2868_tuple_fields, values: [param_1e9efca18e7a2868_dim_1,param_1e9efca18e7a2868_dim_2]} : null"
        }
      ]
    },
    {
      "name": "param_1e9efca18e7a2868_tuple_fields",
      "value": [
        {
          "field": "dim_1",
          "channel": "x",
          "type": "R"
        },
        {
          "field": "dim_2",
          "channel": "y",
          "type": "R"
        }
      ]
    },
    {
      "name": "param_1e9efca18e7a2868_translate_anchor",
      "value": {},
      "on": [
        {
          "events": [
            {
              "source": "scope",
              "type": "pointerdown"
            }
          ],
          "update": "{x: x(unit), y: y(unit), extent_x: domain(\"x\"), extent_y: domain(\"y\")}"
        }
      ]
    },
    {
      "name": "param_1e9efca18e7a2868_translate_delta",
      "value": {},
      "on": [
        {
          "events": [
            {
              "source": "window",
              "between": [
                {
                  "source": "scope",
                  "type": "pointerdown"
                },
                {
                  "source": "window",
                  "type": "pointerup"
                }
              ],
              "consume": true,
              "type": "pointermove"
            }
          ],
          "update": "{x: param_1e9efca18e7a2868_translate_anchor.x - x(unit), y: param_1e9efca18e7a2868_translate_anchor.y - y(unit)}"
        }
      ]
    },
    {
      "name": "param_1e9efca18e7a2868_zoom_anchor",
      "on": [
        {
          "events": [
            {
              "source": "scope",
              "consume": true,
              "type": "wheel"
            }
          ],
          "update": "{x: invert(\"x\", x(unit)), y: invert(\"y\", y(unit))}"
        }
      ]
    },
    {
      "name": "param_1e9efca18e7a2868_zoom_delta",
      "on": [
        {
          "events": [
            {
              "source": "scope",
              "consume": true,
              "type": "wheel"
            }
          ],
          "update": "pow(1.001, event.deltaY * pow(16, event.deltaMode))",
          "force": true
        }
      ]
    },
    {
      "name": "param_1e9efca18e7a2868_modify",
      "on": [
        {
          "events": {
            "signal": "param_1e9efca18e7a2868_tuple"
          },
          "update": "modify(\"param_1e9efca18e7a2868_store\", param_1e9efca18e7a2868_tuple, true)"
        }
      ]
    }
  ],
  "marks": [
    {
      "type": "symbol",
      "name": "marks",
      "from": {
        "data": "source_0"
      },
      "encode": {
        "update": {
          "fill": {
            "value": "#4c78a8"
          },
          "y": {
            "field": "dim_2",
            "scale": "y"
          },
          "x": {
            "field": "dim_1",
            "scale": "x"
          },
          "opacity": {
            "value": 0.8
          },
          "shape": {
            "value": "circle"
          },
          "size": {
            "value": 80
          },
          "tooltip": {
            "signal": "{\"Comment #\": format(datum[\"index\"], \"\"), \"Comment\": isValid(datum[\"comment\"]) ? datum[\"comment\"] : \"\"+datum[\"comment\"]}"
          }
        }
      },
      "clip": true,
      "style": [
        "circle"
      ],
      "interactive": true
    }
  ],
  "scales": [
    {
      "name": "x",
      "type": "linear",
      "domain": [
        {
          "signal": "(data(\"source_0_x_domain_dim_1\")[0] || {}).min"
        },
        {
          "signal": "(data(\"source_0_x_domain_dim_1\")[0] || {}).max"
        }
      ],
      "range": [
        0,
        {
          "signal": "width"
        }
      ],
      "nice": true,
      "domainRaw": {
        "signal": "param_1e9efca18e7a2868[\"dim_1\"]"
      },
      "zero": true
    },
    {
      "name": "y",
      "type": "linear",
      "domain": [
        {
          "signal": "(data(\"source_0_y_domain_dim_2\")[0] || {}).min"
        },
        {
          "signal": "(data(\"source_0_y_domain_dim_2\")[0] || {}).max"
        }
      ],
      "range": [
        {
          "signal": "height"
        },
        0
      ],
      "nice": true,
      "zero": true,
      "domainRaw": {
        "signal": "param_1e9efca18e7a2868[\"dim_2\"]"
      }
    }
  ],
  "axes": [
    {
      "scale": "x",
      "maxExtent": 0,
      "aria": false,
      "tickCount": {
        "signal": "ceil(width/40)"
      },
      "labels": false,
      "gridScale": "y",
      "grid": true,
      "minExtent": 0,
      "ticks": false,
      "zindex": 0,
      "domain": false,
      "orient": "bottom"
    },
    {
      "scale": "y",
      "labels": false,
      "orient": "left",
      "grid": true,
      "maxExtent": 0,
      "minExtent": 0,
      "ticks": false,
      "tickCount": {
        "signal": "ceil(height/40)"
      },
      "zindex": 0,
      "aria": false,
      "gridScale": "x",
      "domain": false
    },
    {
      "scale": "x",
      "tickCount": {
        "signal": "ceil(width/40)"
      },
      "orient": "bottom",
      "zindex": 0,
      "title": "t-SNE 1",
      "labelOverlap": true,
      "labelFlush": true,
      "grid": false
    },
    {
      "scale": "y",
      "tickCount": {
        "signal": "ceil(height/40)"
      },
      "grid": false,
      "title": "t-SNE 2",
      "orient": "left",
      "labelOverlap": true,
      "zindex": 0
    }
  ],
  "title": {
    "text": "Comment similarity (vis 167, n=176) \u2014 t-SNE 2D",
    "fontSize": 14,
    "frame": "group"
  },
  "padding": 5,
  "width": 600,
  "background": "white",
  "height": 500,
  "style": "cell"
}