{
  "$schema": "https://vega.github.io/schema/vega/v6.json",
  "data": [
    {
      "name": "param_1e9efca18e7a2868_store"
    },
    {
      "name": "source_0",
      "values": [
        {
          "comment": "I noticed that only Boeing is on this graph in Aircraft manufacturing market-section. Then, I think \"Boeing\" monopolize \u2026",
          "dim_1": 2.078,
          "dim_2": -9.644,
          "index": 0
        },
        {
          "comment": "I noticed that dr pepper and snapple were doing the worst out of the companies. Bank of America was doing the best out o\u2026",
          "dim_1": 5.593,
          "dim_2": 0.29,
          "index": 1
        },
        {
          "comment": "I noticed that Bank of America has the most value.\n I wonder where Apple is on this graph.\n The graph shows the value of\u2026",
          "dim_1": 6.536,
          "dim_2": 0.595,
          "index": 2
        },
        {
          "comment": "Hi! I am doing these with a class I am teaching that is off-cycle from when they are released/discussed so I need to pri\u2026",
          "dim_1": -2.137,
          "dim_2": 4.715,
          "index": 3
        },
        {
          "comment": "We noticed that the blocks representing the companies are different colours but we are not sure about the connection bet\u2026",
          "dim_1": -6.654,
          "dim_2": -6.209,
          "index": 4
        },
        {
          "comment": "What do you notice?\n-The size of worth is correlated to the size of squares\n-Some squares don't list price\n-The biggest \u2026",
          "dim_1": 0.617,
          "dim_2": -7.593,
          "index": 5
        },
        {
          "comment": "I noticed that on the graph the biggest valued stock was Bank of America. I also notice that Apple and Amazon topped a t\u2026",
          "dim_1": 1.414,
          "dim_2": -6.265,
          "index": 6
        },
        {
          "comment": "I notice that companies I had initially thought to be worth billions, are significantly smaller than some of the other c\u2026",
          "dim_1": 7.605,
          "dim_2": 3.853,
          "index": 7
        },
        {
          "comment": "Greedy Supreme\nI notice 27 companies that are sized by their stock market value. I wonder what companies are doing with \u2026",
          "dim_1": 9.582,
          "dim_2": -2.453,
          "index": 8
        },
        {
          "comment": "In this graph the information i\u2019m pulling is that in year 2018 these 27 companies together have the stock price of a tri\u2026",
          "dim_1": 12.974,
          "dim_2": 1.081,
          "index": 9
        },
        {
          "comment": "A Trillion Dollars\n\nThis seems to be a graph of the corporations leading the stock market. Bank of America seems to be l\u2026",
          "dim_1": 2.564,
          "dim_2": -2.641,
          "index": 10
        },
        {
          "comment": "Bank of America owning the game? There is many things going on in this graph. First thing that came to mind is that ther\u2026",
          "dim_1": 9.841,
          "dim_2": 4.34,
          "index": 11
        },
        {
          "comment": "A Billion A Trillion Boxes\nIn this graph, I notice that Apple's stock market is the highest that they mention. I wonder \u2026",
          "dim_1": 1.868,
          "dim_2": -3.367,
          "index": 12
        },
        {
          "comment": "Bank of America Taking Over\n\nAccording to this graph, Bank of America is ahead of all other companies in the stock reven\u2026",
          "dim_1": 11.406,
          "dim_2": 4.025,
          "index": 13
        },
        {
          "comment": "In this graph there are multiple boxes with areas that increase or decrease depending on their stock market value. There\u2026",
          "dim_1": 5.473,
          "dim_2": -3.644,
          "index": 14
        },
        {
          "comment": "We noticed that the size of the square of the business corresponds with a business\u2019 stock market value (i.e. the more mo\u2026",
          "dim_1": 4.775,
          "dim_2": -2.209,
          "index": 15
        },
        {
          "comment": "A  Rainbow of Trillion Dollars\nThis graph shows the companies different stock markets by using different sizes of boxes.\u2026",
          "dim_1": -3.312,
          "dim_2": -2.924,
          "index": 16
        },
        {
          "comment": "I notice that these are all different types of companies, some of them are so little and don't even have a price on them\u2026",
          "dim_1": 1.485,
          "dim_2": -0.516,
          "index": 17
        },
        {
          "comment": "Business by the Billions and Trillions.  Apple was the first U.S corporation that stock market value reached one trillio\u2026",
          "dim_1": 3.423,
          "dim_2": -1.433,
          "index": 18
        },
        {
          "comment": "I notice in this graph that its about the stocks in the stock market and how much they are worth. I was amazed of how mu\u2026",
          "dim_1": 2.654,
          "dim_2": -6.755,
          "index": 19
        },
        {
          "comment": "Famous Stock Value\n\tI think it\u2019s just the value of some big brands stocks the smaller they are the less valuable they ar\u2026",
          "dim_1": 1.812,
          "dim_2": 3.936,
          "index": 20
        },
        {
          "comment": "I notice that some of the companies that have the same stock market value have a smaller size than some of the companies\u2026",
          "dim_1": -3.282,
          "dim_2": -4.205,
          "index": 21
        },
        {
          "comment": "The first thing we notice about the graph, is that there is large and small boxes. Each box has a name of a company on i\u2026",
          "dim_1": 1.34,
          "dim_2": -1.183,
          "index": 22
        },
        {
          "comment": "The biggest bank in the game is Bank of america. Bank of America has the highest stock market value as of September 2nd.\u2026",
          "dim_1": 9.861,
          "dim_2": 3.099,
          "index": 23
        },
        {
          "comment": "Bank of America Reigns Supreme\n\nI noticed that Bank of America is destroying all the other companies in stock revenue. S\u2026",
          "dim_1": 11.435,
          "dim_2": 4.379,
          "index": 24
        },
        {
          "comment": "I notice that the Bank of America is worth more than every other company. I\u2019m also proud t5o see that Ford is up there b\u2026",
          "dim_1": 9.937,
          "dim_2": 6.107,
          "index": 25
        },
        {
          "comment": "I notice many boxes with the brands names in them. They have a certain amount of money in them. I wonder what they meant\u2026",
          "dim_1": 10.794,
          "dim_2": -7.643,
          "index": 26
        },
        {
          "comment": "In the graph, I notice that there are several businesses that provide their stock values. It looks like the bank of Amer\u2026",
          "dim_1": 6.736,
          "dim_2": -2.118,
          "index": 27
        },
        {
          "comment": "I notice that the Bank of America has the most money in the stock market which is $312 billion. I wonder what \u201cBoeing\u201d i\u2026",
          "dim_1": 9.664,
          "dim_2": 1.293,
          "index": 28
        },
        {
          "comment": "I think that the graph is showing all of the companies and how much money they have made and it's making a statement tha\u2026",
          "dim_1": -0.921,
          "dim_2": 1.606,
          "index": 29
        },
        {
          "comment": "In this graph it is all about the stock market and businesses value. Bank of america is at the top with $312 billion. Dr\u2026",
          "dim_1": 13.457,
          "dim_2": 1.963,
          "index": 30
        },
        {
          "comment": "Stock market on the rise.\nThis looks like a graph showing the stock market rises. I'm not sure if the colors mean someth\u2026",
          "dim_1": 0.968,
          "dim_2": -5.777,
          "index": 31
        },
        {
          "comment": "What I notice in the graph is that all the bigger squares are the bigger companies that have a lot of money and the smal\u2026",
          "dim_1": 0.401,
          "dim_2": -0.42,
          "index": 32
        },
        {
          "comment": "These are the richest companies. I noticed that size of the box the company is in determines how much money they make.  \u2026",
          "dim_1": -5.752,
          "dim_2": -2.003,
          "index": 33
        },
        {
          "comment": "Apple is a powerhouse company. The graph is showing how all of these big companies  are still so far under Apple's stock\u2026",
          "dim_1": 6.391,
          "dim_2": -0.847,
          "index": 34
        },
        {
          "comment": "In this graph there are 27 companies that are sized accordingly to their stock market size. I noticed that the bigger co\u2026",
          "dim_1": -0.776,
          "dim_2": -4.6,
          "index": 35
        },
        {
          "comment": "I wonder if this is the beginning of the Apple logo. I'm guessing this is right over $1 trillion so Apple can be the nex\u2026",
          "dim_1": 3.354,
          "dim_2": 0.069,
          "index": 36
        },
        {
          "comment": "apple is the richest company and all these companies combind are worth a trillion and i didn't that footlocker was that \u2026",
          "dim_1": 2.375,
          "dim_2": 1.213,
          "index": 37
        },
        {
          "comment": "C:This graph shows  Apple's stock market value, and how their value compares to other companies.\nE:And at the bottom of \u2026",
          "dim_1": 4.097,
          "dim_2": -4.802,
          "index": 38
        },
        {
          "comment": "I notice that bank of America has the highest stock market value. I wonder why that is. And what might be going on in th\u2026",
          "dim_1": 10.461,
          "dim_2": 1.867,
          "index": 39
        },
        {
          "comment": "I noticed that Bank of America has the highest stock market value as of September 2nd. This is because  Bank of America \u2026",
          "dim_1": 11.445,
          "dim_2": 0.632,
          "index": 40
        },
        {
          "comment": "I notice one of one  company are  the lowest in the company with  some help from  other and some lost almost the value t\u2026",
          "dim_1": 5.079,
          "dim_2": 2.612,
          "index": 41
        },
        {
          "comment": "I noticed that Bank of America has the highest stock market value as of September 2nd. This is because  Bank of America \u2026",
          "dim_1": 11.101,
          "dim_2": 0.804,
          "index": 42
        },
        {
          "comment": "I notice that the biggest boxes are the one with the most to differentiate the success of others and the amount of money\u2026",
          "dim_1": -5.268,
          "dim_2": 0.516,
          "index": 43
        },
        {
          "comment": "Each business has different million of investment. The apple company gave a 1,000,000,000,000 dollar to each company. I \u2026",
          "dim_1": -1.705,
          "dim_2": 0.96,
          "index": 44
        },
        {
          "comment": "I notice Bank of America is the Biggest and highest amount more than any other company.\nI wonder how Bank of America is \u2026",
          "dim_1": 8.608,
          "dim_2": 4.183,
          "index": 45
        },
        {
          "comment": "I NOTICE A LOT OF COMPANIES  ARE ALL WORKING EVEN THOUGH THEY SELL DIFFERENTE THING, THEY HAVE THE SAME PURPOSE, THAT IS\u2026",
          "dim_1": 10.15,
          "dim_2": -7.573,
          "index": 46
        },
        {
          "comment": "One trillion dollars not only has a lot of zeros (12!), but is equal to the sum of the stock values of 27 popular U. S. \u2026",
          "dim_1": 0.537,
          "dim_2": -2.241,
          "index": 47
        },
        {
          "comment": "I noticed all of the companies in the boxes and saw that this graph has to do with money. I noticed that the smaller box\u2026",
          "dim_1": -4.244,
          "dim_2": -1.139,
          "index": 48
        },
        {
          "comment": "I noticed that this is a stock market for companies and i also wonder how apple is worth so much money. A good title for\u2026",
          "dim_1": 3.148,
          "dim_2": -5.332,
          "index": 49
        },
        {
          "comment": "I notice that this graph  is full of well known world wide companies. Also that Bank of America has more money than all \u2026",
          "dim_1": 7.452,
          "dim_2": 1.966,
          "index": 50
        },
        {
          "comment": "how far will they go is there a way to estimate how much money they will make in the future and is there a chance for an\u2026",
          "dim_1": -8.327,
          "dim_2": 0.511,
          "index": 51
        },
        {
          "comment": "I noticed this was about Bank because I saw Bank of America that I only know. and I think the size of each says how much\u2026",
          "dim_1": 6.874,
          "dim_2": 5.304,
          "index": 52
        },
        {
          "comment": "I notice different companies. Some with their stock market value and without.\nI wonder why some of the stock market valu\u2026",
          "dim_1": 5.961,
          "dim_2": -5.479,
          "index": 53
        },
        {
          "comment": "I noticed that the chart have many boxes with a different proportion and every box have the name of a big corporation. I\u2026",
          "dim_1": -4.257,
          "dim_2": 1.102,
          "index": 54
        },
        {
          "comment": "I noticed that the smaller boxes do not have any numbers in them, which could be significant, but is not seen as if is n\u2026",
          "dim_1": -7.017,
          "dim_2": -3.224,
          "index": 55
        },
        {
          "comment": "I noticed that not every corporation the graph has not their marketing number. For example, Ralph Lauren, Foot Locker, N\u2026",
          "dim_1": 7.287,
          "dim_2": -4.102,
          "index": 56
        },
        {
          "comment": "I notice big company brand names and the bottom companies are like the bases because they are the larger companies that \u2026",
          "dim_1": -7.328,
          "dim_2": -6.044,
          "index": 57
        },
        {
          "comment": "In this graph there are multiple boxes with areas that increase or decrease depending on their stock market value. Also,\u2026",
          "dim_1": 5.708,
          "dim_2": -3.877,
          "index": 58
        },
        {
          "comment": "How come companies like microsoft and apple were not included?",
          "dim_1": 9.107,
          "dim_2": -7.311,
          "index": 59
        },
        {
          "comment": "I notice that some of the companies that have the same stock market value have a smaller size than some of the companies\u2026",
          "dim_1": -2.409,
          "dim_2": -5.524,
          "index": 60
        },
        {
          "comment": "i notice that it shows how much the stock market value is for the companies listed/shown, but only for really big compan\u2026",
          "dim_1": -6.131,
          "dim_2": -5.565,
          "index": 61
        },
        {
          "comment": "I notice that Bank of America makes the most money out of these companies. What is included in the $312 billion from Ban\u2026",
          "dim_1": 8.476,
          "dim_2": 6.354,
          "index": 62
        },
        {
          "comment": "I notice boxes representing different companies. I think the trillion represents the combined amount of revenue from eac\u2026",
          "dim_1": -5.028,
          "dim_2": 3.585,
          "index": 63
        },
        {
          "comment": "I notice there are some brands on the graph without a net worth so I wonder if they all below $10 billions. Headline: \"W\u2026",
          "dim_1": 4.729,
          "dim_2": -8.871,
          "index": 64
        },
        {
          "comment": "I noticed that all of these companies have a certain size to determine how big successful their company is. The larger t\u2026",
          "dim_1": -6.825,
          "dim_2": 0.33,
          "index": 65
        },
        {
          "comment": "I notice that the title is 1,000,000 dollars and it talks about how Apple and Amazon's stock market value both surpassed\u2026",
          "dim_1": 3.902,
          "dim_2": -2.556,
          "index": 66
        },
        {
          "comment": "I notice that the biggest boxes are the one with the most to differentiate the success of others and the amount of money\u2026",
          "dim_1": -5.268,
          "dim_2": 0.516,
          "index": 67
        },
        {
          "comment": "So the first thing i noticed are the colors and how it is one trillion, then the next thing i noticed is that the bank o\u2026",
          "dim_1": -0.649,
          "dim_2": -2.036,
          "index": 68
        },
        {
          "comment": "I noticed that none of the largest boxes are relatively the same size. I wonder how these companie were placed, like why\u2026",
          "dim_1": -5.144,
          "dim_2": -2.901,
          "index": 69
        },
        {
          "comment": "I am surprised by the amount of money shown here, but i expected disney to make much more money than shown here based on\u2026",
          "dim_1": 2.271,
          "dim_2": 9.059,
          "index": 70
        },
        {
          "comment": "I wonder if the companies with the largest stock market value also have the biggest impact in society.",
          "dim_1": 12.249,
          "dim_2": -1.024,
          "index": 71
        },
        {
          "comment": "I thought disney would make more money",
          "dim_1": 2.277,
          "dim_2": 9.059,
          "index": 72
        },
        {
          "comment": "I notice it says 1 trillion Dollars, and that banks has the most amount of the money. Also the biggest company had the b\u2026",
          "dim_1": -6.399,
          "dim_2": 2.475,
          "index": 73
        },
        {
          "comment": "I noticed that they are another trillion dollars and the boxes names are more bold if  they have more money.",
          "dim_1": -6.644,
          "dim_2": 3.643,
          "index": 74
        },
        {
          "comment": "i notice it says 1 trillion Dollars, another thing i notice is names of big companies in boxes, also the bigger the comp\u2026",
          "dim_1": -6.005,
          "dim_2": 2.7,
          "index": 75
        },
        {
          "comment": "Welcome to \u201cWhat\u2019s Going On in This Graph?\u201d.  Recently, a few American public corporations topped a stock market value o\u2026",
          "dim_1": -0.628,
          "dim_2": -8.478,
          "index": 76
        },
        {
          "comment": "I notice that the sum of the market capitalizations of these companies  are roughly (if-not-exactly) equal to one trilli\u2026",
          "dim_1": 8.116,
          "dim_2": -6.433,
          "index": 77
        },
        {
          "comment": "I notice that the graph contains American companies that have reached at least a billion dollars in stock market value. \u2026",
          "dim_1": 1.699,
          "dim_2": -7.95,
          "index": 78
        }
      ]
    },
    {
      "name": "source_0_x_domain_dim_1",
      "values": [
        {
          "min": -8.327,
          "max": 13.457
        }
      ]
    },
    {
      "name": "source_0_y_domain_dim_2",
      "values": [
        {
          "min": -9.644,
          "max": 9.059
        }
      ]
    }
  ],
  "signals": [
    {
      "name": "unit",
      "value": {},
      "on": [
        {
          "events": "pointermove",
          "update": "isTuple(group()) ? group() : unit"
        }
      ]
    },
    {
      "name": "param_1e9efca18e7a2868",
      "update": "vlSelectionResolve(\"param_1e9efca18e7a2868_store\", \"union\")"
    },
    {
      "name": "param_1e9efca18e7a2868_dim_1",
      "on": [
        {
          "events": [
            {
              "source": "view",
              "type": "dblclick"
            }
          ],
          "update": "null"
        },
        {
          "events": {
            "signal": "param_1e9efca18e7a2868_translate_delta"
          },
          "update": "panLinear(param_1e9efca18e7a2868_translate_anchor.extent_x, -param_1e9efca18e7a2868_translate_delta.x / width)"
        },
        {
          "events": {
            "signal": "param_1e9efca18e7a2868_zoom_delta"
          },
          "update": "zoomLinear(domain(\"x\"), param_1e9efca18e7a2868_zoom_anchor.x, param_1e9efca18e7a2868_zoom_delta)"
        }
      ]
    },
    {
      "name": "param_1e9efca18e7a2868_dim_2",
      "on": [
        {
          "events": [
            {
              "source": "view",
              "type": "dblclick"
            }
          ],
          "update": "null"
        },
        {
          "events": {
            "signal": "param_1e9efca18e7a2868_translate_delta"
          },
          "update": "panLinear(param_1e9efca18e7a2868_translate_anchor.extent_y, param_1e9efca18e7a2868_translate_delta.y / height)"
        },
        {
          "events": {
            "signal": "param_1e9efca18e7a2868_zoom_delta"
          },
          "update": "zoomLinear(domain(\"y\"), param_1e9efca18e7a2868_zoom_anchor.y, param_1e9efca18e7a2868_zoom_delta)"
        }
      ]
    },
    {
      "name": "param_1e9efca18e7a2868_tuple",
      "on": [
        {
          "events": [
            {
              "signal": "param_1e9efca18e7a2868_dim_1 || param_1e9efca18e7a2868_dim_2"
            }
          ],
          "update": "param_1e9efca18e7a2868_dim_1 && param_1e9efca18e7a2868_dim_2 ? {unit: \"\", fields: param_1e9efca18e7a2868_tuple_fields, values: [param_1e9efca18e7a2868_dim_1,param_1e9efca18e7a2868_dim_2]} : null"
        }
      ]
    },
    {
      "name": "param_1e9efca18e7a2868_tuple_fields",
      "value": [
        {
          "field": "dim_1",
          "channel": "x",
          "type": "R"
        },
        {
          "field": "dim_2",
          "channel": "y",
          "type": "R"
        }
      ]
    },
    {
      "name": "param_1e9efca18e7a2868_translate_anchor",
      "value": {},
      "on": [
        {
          "events": [
            {
              "source": "scope",
              "type": "pointerdown"
            }
          ],
          "update": "{x: x(unit), y: y(unit), extent_x: domain(\"x\"), extent_y: domain(\"y\")}"
        }
      ]
    },
    {
      "name": "param_1e9efca18e7a2868_translate_delta",
      "value": {},
      "on": [
        {
          "events": [
            {
              "source": "window",
              "between": [
                {
                  "source": "scope",
                  "type": "pointerdown"
                },
                {
                  "source": "window",
                  "type": "pointerup"
                }
              ],
              "consume": true,
              "type": "pointermove"
            }
          ],
          "update": "{x: param_1e9efca18e7a2868_translate_anchor.x - x(unit), y: param_1e9efca18e7a2868_translate_anchor.y - y(unit)}"
        }
      ]
    },
    {
      "name": "param_1e9efca18e7a2868_zoom_anchor",
      "on": [
        {
          "events": [
            {
              "source": "scope",
              "consume": true,
              "type": "wheel"
            }
          ],
          "update": "{x: invert(\"x\", x(unit)), y: invert(\"y\", y(unit))}"
        }
      ]
    },
    {
      "name": "param_1e9efca18e7a2868_zoom_delta",
      "on": [
        {
          "events": [
            {
              "source": "scope",
              "consume": true,
              "type": "wheel"
            }
          ],
          "update": "pow(1.001, event.deltaY * pow(16, event.deltaMode))",
          "force": true
        }
      ]
    },
    {
      "name": "param_1e9efca18e7a2868_modify",
      "on": [
        {
          "events": {
            "signal": "param_1e9efca18e7a2868_tuple"
          },
          "update": "modify(\"param_1e9efca18e7a2868_store\", param_1e9efca18e7a2868_tuple, true)"
        }
      ]
    }
  ],
  "marks": [
    {
      "type": "symbol",
      "name": "marks",
      "from": {
        "data": "source_0"
      },
      "encode": {
        "update": {
          "fill": {
            "value": "#4c78a8"
          },
          "shape": {
            "value": "circle"
          },
          "y": {
            "field": "dim_2",
            "scale": "y"
          },
          "size": {
            "value": 80
          },
          "tooltip": {
            "signal": "{\"Comment #\": format(datum[\"index\"], \"\"), \"Comment\": isValid(datum[\"comment\"]) ? datum[\"comment\"] : \"\"+datum[\"comment\"]}"
          },
          "opacity": {
            "value": 0.8
          },
          "x": {
            "field": "dim_1",
            "scale": "x"
          }
        }
      },
      "clip": true,
      "interactive": true,
      "style": [
        "circle"
      ]
    }
  ],
  "scales": [
    {
      "name": "x",
      "type": "linear",
      "domain": [
        {
          "signal": "(data(\"source_0_x_domain_dim_1\")[0] || {}).min"
        },
        {
          "signal": "(data(\"source_0_x_domain_dim_1\")[0] || {}).max"
        }
      ],
      "range": [
        0,
        {
          "signal": "width"
        }
      ],
      "zero": true,
      "nice": true,
      "domainRaw": {
        "signal": "param_1e9efca18e7a2868[\"dim_1\"]"
      }
    },
    {
      "name": "y",
      "type": "linear",
      "domain": [
        {
          "signal": "(data(\"source_0_y_domain_dim_2\")[0] || {}).min"
        },
        {
          "signal": "(data(\"source_0_y_domain_dim_2\")[0] || {}).max"
        }
      ],
      "range": [
        {
          "signal": "height"
        },
        0
      ],
      "nice": true,
      "zero": true,
      "domainRaw": {
        "signal": "param_1e9efca18e7a2868[\"dim_2\"]"
      }
    }
  ],
  "axes": [
    {
      "scale": "x",
      "orient": "bottom",
      "tickCount": {
        "signal": "ceil(width/40)"
      },
      "gridScale": "y",
      "zindex": 0,
      "aria": false,
      "maxExtent": 0,
      "grid": true,
      "domain": false,
      "ticks": false,
      "minExtent": 0,
      "labels": false
    },
    {
      "scale": "y",
      "zindex": 0,
      "tickCount": {
        "signal": "ceil(height/40)"
      },
      "minExtent": 0,
      "grid": true,
      "orient": "left",
      "labels": false,
      "domain": false,
      "aria": false,
      "maxExtent": 0,
      "ticks": false,
      "gridScale": "x"
    },
    {
      "scale": "x",
      "labelOverlap": true,
      "title": "t-SNE 1",
      "zindex": 0,
      "orient": "bottom",
      "tickCount": {
        "signal": "ceil(width/40)"
      },
      "grid": false,
      "labelFlush": true
    },
    {
      "scale": "y",
      "grid": false,
      "zindex": 0,
      "orient": "left",
      "title": "t-SNE 2",
      "labelOverlap": true,
      "tickCount": {
        "signal": "ceil(height/40)"
      }
    }
  ],
  "title": {
    "text": "Comment similarity (vis 204, n=79) \u2014 t-SNE 2D",
    "frame": "group",
    "fontSize": 14
  },
  "background": "white",
  "style": "cell",
  "height": 500,
  "padding": 5,
  "width": 600
}