{
  "article_id": "123",
  "comment_index": 148,
  "image_path": "../data/images/123.png",
  "numbered_ace_sentences": [
    "1. I look at the graph.",
    "2. I notice that a majority of 15-24 year olds are convinced that newer generations make the world a better place.",
    "3. I wonder if the people who think that the world is changing and becoming better will do something to change the world.",
    "4. I do not say that this relates to me very much.",
    "5. I hear people talking about the world.",
    "6. Most of these people say that the world is getting worse.",
    "7. The headline is: The world is changing?"
  ],
  "presence_tags": {
    "1. 1. I look at the graph.": "not_present",
    "2. 2. I notice that a majority of 15-24 year olds are convinced that newer generations make the world a better place.": "not_present",
    "3. 3. I wonder if the people who think that the world is changing and becoming better will do something to change the world.": "not_present",
    "4. 4. I do not say that this relates to me very much.": "not_present",
    "5. 5. I hear people talking about the world.": "not_present",
    "6. 6. Most of these people say that the world is getting worse.": "not_present",
    "7. 7. The headline is: The world is changing?": "not_present"
  }
}